{"Adipocyte cell": ["1500017E21Rik", "Adig", "Plin1", "Gm14964", "Synm", "C1qtnf7", "Lrp3", "Rasgrf2", "Plcl1", "Kng2", "Lrrn3", "Mark1", "9030407P20Rik", "Mc2r", "Six1", "Efemp1", "Pla1a", "Lpl", "Il1rn", "Tmem178", "Cfd", "Smoc1", "Fbln1", "Gm14648", "Mir99ahg", "Pparg", "2510009E07Rik", "Adipoq", "A430018G15Rik", "Zfp629", "Mical2", "Crim1", "9130023H24Rik", "Lamc1", "Slc1a3", "2810408A11Rik", "Gsta4", "Mras", "Angptl6", "Gpr27", "Ralgapa2", "Xylt2", "Emp1", "Fam179b", "Sipa1l2", "Lamb1", "Gm16378", "Cxcl12", "Mtss1l", "Mccc1"], "Ascending loop of Henle": ["Umod", "Gm7556", "Prrg4", "Igkv4-57", "Rps11-ps3", "Klk1", "C920021L13Rik", "Gm15946", "Pgam2", "Cd4", "Cdc14b", "Gm43305", "Hsd17b7", "Galnt7", "Tpcn2", "Gm42759", "Hltf", "Card6", "Slc10a7", "Fbrsl1", "P2ry13", "B4galt4", "Dpy19l4", "Polr3a", "1810014B01Rik", "Afdn", "Zfp87", "Phf11b", "Arl6", "Exoc1", "Slc33a1", "Acadsb", "Saysd1", "Sufu", "Zswim1", "Map3k2", "Trak2", "Ccr9", "Mipep", "Eno3", "Lrch1", "Htt", "Sh3bp2", "Ikbkap", "Diaph2", "Fbxo33", "Ccnd1", "Stxbp5", "Rcor1", "Caap1"], "B cell": ["Vpreb3", "Myl4", "Cd79a", "Igll1", "Ebf1", "Chchd10", "Blnk", "Vpreb1", "Pou2af1", "Cd79b", "Cd19", "Mzb1", "Fcrla", "Spib", "Pafah1b3", "Ptprcap", "Tifa", "Cnp", "Lrmp", "Smarca4", "Slc1a5", "Dusp2", "Ly6d", "Snx2", "Pkig", "Ptma", "Ucp2", "Arpc5l", "Dnajc7", "Ptp4a3", "Lgals9", "Crip1", "Tspan13", "Cd24a", "Siglecg", "Hmgb1", "Pclaf", "H2afv", "Ezh2", "Elof1", "Zfp706", "Anp32e", "Apobec3", "Hmgn1", "Herpud1", "Cbx1", "Serinc3", "Tubb5", "Dnajc9", "Tmsb10"], "Cardiomyocyte": ["Abcb6", "4632411P08Rik", "Myl2", "Gm9796", "Rwdd2b", "B3gntl1", "Arrdc2", "Tatdn3", "Gm4342", "Zfp938", "Carmil2", "Slc39a13", "Ube2t", "Rpph1", "Lipo3", "Slc25a35", "Agpat3", "Crem", "Ptgr2", "Zxdb", "Nmnat3", "Plcg1", "Usp24", "Gtpbp8", "Sh3pxd2a", "Mfsd2b", "Ppcs", "Slc35e3", "Hist1h2bj", "Irak4", "Rab3il1", "Gm5436", "Timm8a1", "Abcg4", "Cep290", "Znhit3", "Scpep1", "Adat1", "Palb2", "Rgs12", "Acsl3", "6330562C20Rik", "Tprkb", "Ccdc6", "Akap12", "Ncbp2", "Ppp6c", "Tex264", "Pgam5", "Rras"], "Chondrocyte": ["Col2a1", "Cnmd", "Col9a1", "Col9a2", "Col9a3", "3110079O15Rik", "Hapln1", "Mia", "Matn3", "Acan", "Comp", "Fxyd2", "Epyc", "Chad", "Col27a1", "Ppa1", "Fmod", "Scrg1", "Ucma", "Ncmap", "Prelp", "Pcolce2", "Sox9", "1500015O10Rik", "Mfge8", "S100b", "C1qtnf3", "Dhx58os", "Il17b", "Syt8", "Panx3", "Fam180a", "Cdkn1c", "Fxyd3", "Cox4i2", "Matn1", "Susd5", "Colgalt2", "Crispld1", "Meltf", "Angptl2", "Nrep", "Fgfr3", "Fbln7", "Rasd1", "Tubb2a", "Car12", "Anxa8", "Sdc4", "Papss2"], "Connecting tubule cell": ["Spp1", "Mmp13", "Rbp4", "Mgp", "Steap4", "Col10a1", "R3hdml", "Fn1", "Enpp1", "Fam20c", "Ddit4l", "Sdc1", "Tnc", "Htra1", "Ctgf", "Ank", "Serpine2", "Timp1", "Srpx2", "Col6a3", "Matn1", "Sfrp4", "Sdc2", "Emp1", "Col3a1", "Ibsp", "Aebp1", "Col6a1", "Fgfr1", "Col6a2", "Phlda1", "Prnp", "Chad", "Clu", "S100a16", "Hpgd", "Slc29a1", "Cdkn1a", "F13a1", "Ccdc80", "Angptl4", "Gpx3", "Pth1r", "Cst3", "Egr1", "Mia", "Acan", "1500015O10Rik", "Sgk1", "Cpe"], "Dendritic cell": ["H2-Ab1", "H2-Aa", "Cd74", "H2-Eb1", "Cox6a2", "Rnase6", "Siglech", "Irf8", "H2-DMb1", "Bst2", "Pld4", "Cd7", "Phf11b", "Mpeg1", "Cst3", "Itgb7", "H2-DMa", "Psap", "Ly6d", "Ptms", "Evi2a", "Gm2a", "Ctss", "Crip1", "Ccr2", "Aif1", "Ctsl", "Lsp1", "Arhgap17", "Kctd12", "Selplg", "Ifi30", "Tmsb10", "Anxa6", "Ppt1", "Id2", "Ctsh", "Tspan13", "Cd48", "Plbd1", "Gltp", "Grn", "Ly6e", "Ifi27l2a", "Klf2", "Unc93b1", "Laptm5", "Psmb8", "Fth1", "H2-D1"], "Embryonic stem cell": ["Igsf9", "Gm13339", "Saa3", "1700028N14Rik", "Gm5600", "Ttf1", "Btf3l4", "0610040B10Rik", "Gm10136", "Mfsd3", "Il13ra1", "Tdrd3", "Fam76b", "Cep76", "Lsm11", "Chd2", "Polr1b", "H2-T22", "Lpin2", "Rab11fip1", "Dgkg", "Ctbp2", "Wtap", "Gm7331", "Gm5914", "Alcam", "BC055324", "Sppl3", "Snap47", "Pccb", "Ccl27a", "Gm6654", "Zfp710", "Col4a3bp", "Kbtbd7", "Slc43a2", "Gm20492", "Gpalpp1", "Med1", "Dcaf15", "Smarcc1", "Mlh1", "Gm15658", "Crat", "Slc4a1ap", "Gm5963", "Uhmk1", "Ccdc82", "Dpp8", "Lat"], "Endothelial cell": ["Plvap", "Emcn", "Col4a1", "Cldn5", "Cdh5", "Col4a2", "Gpihbp1", "Ramp2", "Esam", "Mmrn2", "Kdr", "Fabp4", "Ecscr", "Ly6c1", "Fam167b", "1810011O10Rik", "Tmem88", "Clec14a", "Igfbp7", "Ushbp1", "Flt1", "Gng11", "Ptprb", "Egfl7", "F11r", "Tmem204", "Aplnr", "Tspan18", "Adgrf5", "8430408G22Rik", "Tm4sf1", "Epas1", "Slc9a3r2", "Adamts1", "Plpp3", "Plk2", "Tfpi", "Eng", "Plpp1", "Cav1", "Thbd", "Stab2", "Rbp1", "Timp3", "Stab1", "Jup", "Pecam1", "S100a16", "Prkcdbp", "Ly6a"], "Enterocyte": ["Plekha7", "Rasal1", "Syngr4", "Ccnj", "Sepsecs", "Ccdc126", "Ankrd24", "Asb13", "Gphn", "Trmt5", "Actr5", "Cdk5rap1", "Flt3", "Caml", "Osgin2", "Rps3a3", "Npl", "Blk", "Nfya", "Mad2l2", "Mtmr2", "Alcam", "Slc35b4", "Tmem19", "Zfp688", "Stat4", "Sec24b", "Map3k8", "Abcf3", "Phf2", "Sap18b", "Polr1e", "Tbkbp1", "Dna2", "Rnf139", "Sec23a", "Satb1", "Abhd17b", "Dhx9", "Mepce", "Fnbp4", "Gps1", "Ginm1", "Thoc1", "Ehd4", "Nkap", "Ift52", "1110004E09Rik", "Rwdd4a", "Tmem109"], "Epithelial cell": ["Zfp781", "Alms1-ps1", "Gm9830", "Gm10657", "Mmp3", "Extl1", "Chmp4c", "6330403L08Rik", "Hspa12a", "Wfdc6a", "Ajuba", "Crabp2", "Olfr482", "Pdzrn3", "Mr1", "Gm22818", "Akr1b8", "Lgals2", "Kng1", "Dip2a", "Gm5321", "Gm15697", "Ubtd2", "Gm18867", "Podnl1", "Dclk2", "Plat", "Chst1", "Tgfb2", "Col6a1", "Tnfsf11", "Ecm1", "Amotl2", "Col5a3", "Bmp4", "Bmp5", "Rsph3a", "Rpl31-ps16", "Nfatc2", "Gm11221", "Sybu", "Ndn", "Gsta4", "Glmn", "Zbtb7c", "Hid1", "Anxa8", "Adgra3", "Rab11b-ps2", "Sod3"], "Erythroblast": ["Car1", "Mt2", "Sphk1", "Car2", "Gm15915", "Ces2g", "Fam132a", "Npm1", "Klf1", "Bex4", "Mthfd1", "Casp3", "Gstm5", "Hspe1", "Mrpl52", "Aqp1", "Gm11361", "Ermap", "Rpl14", "Tspo2", "Blvrb", "Rpl27", "Hspd1", "Rps5", "Rplp1", "Mt1", "Rpl36", "Cela1", "C1qbp", "Cox6b2", "Gata1", "Mns1", "Gas5", "Rps2", "Rpl18", "Minpp1", "Rps26", "Vamp5", "Pla2g12a", "Rpl12", "Rps17", "Rps20", "Rps12", "Rpl11", "1110038B12Rik", "Zfas1", "Rps8", "Hmgb3", "Rfesd", "Asns"], "Erythroid cell": ["Hbb-bt", "Hba-a1", "Hbb-bs", "Gypa", "Ctse", "Hmbs", "Blvrb", "Cldn13", "Rhd", "Car2", "Prdx2", "Hemgn", "Hebp1", "Hba-a2", "Isg20", "Tmem14c", "Alad", "Mgst3", "Klf1", "Nxpe2", "Cpox", "Aqp1", "Smim1", "Fech", "Glrx5", "Urod", "Hagh", "Ermap", "Fth1", "Fam132a", "Tspo2", "Pla2g16", "Tfrc", "Hmgb3", "Rfesd", "Rps2", "Acp1", "Minpp1", "Metap2", "Bola3", "Pla2g12a", "Cd24a", "Prdx3", "Mns1", "Ifrd2", "Rad23a", "Josd2", "Rrm2", "Gstm5", "Selenbp1"], "Fibroblast": ["Serpinf1", "Col5a2", "Sparc", "Ifitm5", "Col1a2", "Dcn", "Lum", "Cthrc1", "Cgref1", "Cpe", "Col1a1", "Bgn", "Fkbp7", "Pcolce", "Car3", "Serpinh1", "Rcn3", "Lox", "Col11a1", "Cpz", "Snhg18", "Gpx8", "Mmp2", "Id3", "Kazald1", "Cfh", "Copz2", "Tmem119", "Gpx3", "Col11a2", "Fap", "Selenom", "Fxyd1", "Cdo1", "Kdelr3", "Cryab", "Gja1", "Ppic", "Wisp1", "Ptgis", "Bambi", "Slc36a2", "Prss35", "Vkorc1", "Col22a1", "Bglap2", "Fkbp10", "Olfml3", "Smpd3", "Nrp2"], "Gastric epithelial cell": ["Atp4b", "Gm5391", "Igkv12-89", "Ppp1r16b", "Gm37510", "Syt11", "Zkscan5", "H2-T10", "Hist1h4f", "Mllt11", "Xrcc2", "Gm42418", "Nr2c1", "Ggnbp1", "Slc25a53", "Pex26", "Yod1", "Tdpx-ps1", "Akt3", "4930503L19Rik", "Gpt", "Extl2", "Insig1", "Hinfp", "Smarcal1", "Haus6", "Gm25360", "1810044D09Rik", "Tbc1d7", "Zfp639", "Ercc2", "Lpin2", "Ift22", "Zfp644", "Pex13", "Dpy19l4", "Pgm1", "Ext2", "Ehmt1", "Cep44", "Cep85", "Papss1", "Ctdspl", "2210016L21Rik", "Casd1", "Srsf9", "Zfp263", "Pcgf1", "Lrrc40", "Tnrc6c"], "Hepatocyte": ["Afp", "Pik3c3", "Atp2c1", "Eef2kmt", "Cars", "Ddx24", "Vta1", "Brd8", "Snd1", "Spop", "Sptbn1", "Smc3", "Dmkn", "Prim2", "Elovl5", "Med9", "Anapc2", "Dnajc15", "Vmp1", "Nqo2", "Trappc3", "Rab44", "Ilf2", "Acyp1", "Jund", "Gtf3c6", "Cfap20", "Set", "Mrps24", "Rpl38-ps2", "Ube2r2", "Ramp1", "Zcchc17", "Stt3b", "Actn1", "Copa", "Snhg9", "Trappc2l", "Ftl1-ps1", "Slc38a2", "Tbcb", "Rps11-ps1", "Baz1a", "Rpl36a-ps2", "Preb", "Ccna2", "Glrx3", "Rpl10a-ps1", "Phgdh", "Ppid"], "Macrophage": ["C1qc", "C1qb", "C1qa", "Fcna", "Hmox1", "Axl", "Apoe", "Vcam1", "Itgad", "Pld3", "Cd5l", "Ms4a7", "Kcnj10", "Mrc1", "Trf", "Maf", "Ccr3", "Spic", "Igf1", "Cd163", "Adgre1", "Mertk", "Aif1", "Slc40a1", "Selenop", "Il18", "Cd68", "Sdc3", "Ctsb", "Cfp", "Clec4b1", "Clec4a3", "Mafb", "Lrp1", "Ctsc", "H2-Eb1", "Ctss", "Lgmn", "Clec4a1", "Cd300c2", "Lpl", "Gngt2", "Fam213b", "Ctsd", "Ftl1", "Glul", "Csf1r", "Sirpa", "H2-Aa", "Gns"], "Mast cell": ["Cpa3", "Prss34", "Mcpt8", "Fcer1a", "Ms4a2", "Cd200r3", "Ccl3", "Ier3", "Gata2", "Ccl4", "Csrp3", "Rgs1", "Cd69", "Ifitm1", "Nfkbia", "Lat2", "Rgs2", "Jun", "Ly6e", "H3f3b", "Hist1h2bc", "Ccl9", "Ier2", "Lmo4", "Adgrg1", "Srgn", "Hist1h1c", "Dapp1", "Hdc", "Hspa5", "Cd63", "Junb", "Calr", "Jund", "Hsp90b1", "Nucb1", "Ubb", "Plac8", "Fxyd5", "2410006H16Rik", "Srsf5", "Gng12", "Cdk6", "S100a10", "Crip1", "Dnaja1", "Neat1", "Dusp1", "Myl12b", "Zfp36"], "Megakaryocyte": ["Pf4", "F2rl2", "Gp1bb", "Treml1", "Sdpr", "Gp9", "Vwf", "Itga2b", "Rab27b", "Gp5", "Nrgn", "Slc14a1", "F2r", "Plek", "Itgb3", "Rabgap1l", "Lat", "Ctla2a", "Serpina3g", "Rgs18", "Pbx1", "Rap1b", "Fam212a", "Pdzk1ip1", "Adgrg1", "Pdcd4", "Dok2", "Samd14", "Ppif", "Dapp1", "Tbxas1", "Tmem40", "Elf1", "Map4k1", "Sord", "Tuba8", "Mef2c", "Cd9", "Rgs10", "Nt5c3", "Prkar2b", "Tspan4", "Serpine2", "Ckap2l", "Pttg1ip", "Lmo2", "Chchd6", "Rsu1", "Lims1", "Gng11"], "Mesenchymal cell": ["Apod", "Cdon", "Tnxb", "Cilp", "C1ra", "Loxl1", "Serping1", "Aebp1", "Col3a1", "Sod3", "Fbln7", "Il11ra1", "Pdgfra", "Gsn", "Ang", "Ltbp4", "Clu", "Fn1", "Colec12", "Tfb1m", "Gpx3", "Ecm1", "Matn1", "Mt2", "Myc", "Fads1", "Ly6c1", "Phlda1", "Rrad", "Steap3", "Col6a2", "Pfkm", "Egr1", "Dcn", "Mrpl49", "Ly6a", "Hspb1", "Rnase4", "Gpank1", "Fstl1", "Col6a1", "Nae1", "1190007I07Rik", "Mt1", "Esyt2", "Pcsk6", "Ctsl", "Sirt2", "Pja1", "Emp1"], "Microglia": ["D5Ertd615e", "Rtn2", "Zfp658", "Siglech", "Gm21762", "A430105J06Rik", "Clec9a", "Gm4189", "Gm7854", "Apc", "Arhgef10l", "Upb1", "Dusp7", "Fggy", "Eepd1", "Tubb2b", "Batf3", "Slc27a1", "Ipp", "Pacsin1", "Gm4045", "Prkab2", "9130221H12Rik", "Klf16", "Hist1h3i", "Elk1", "Slc5a6", "Aak1", "Coq8a", "Mfsd8", "Lrba", "Top3a", "Phc3", "Zc3h8", "Pkp3", "Nckipsd", "Scrn1", "Slc25a53", "Rpgrip1", "Vav2", "Cdk5rap1", "Zbed3", "Gm5547", "Fbxw4", "Mrps18b", "Slx1b", "0610010F05Rik", "Ccr9", "Gpatch8", "Proser1"], "Monocyte": ["S100a4", "Ms4a4c", "Ccr2", "Ms4a6c", "Ifi30", "Psap", "Ctss", "Lgals3", "Ifi27l2a", "Lyz2", "Tgfbi", "Crip1", "F13a1", "Wfdc17", "Pld4", "Ms4a6b", "Ifitm3", "Ccl6", "Ly6e", "Mpeg1", "Tmsb10", "Smpdl3a", "Samhd1", "S100a10", "Ctsc", "Ccl9", "Shisa5", "Ly6c2", "Lsp1", "Tpd52", "Fn1", "Ctsh", "Cd68", "Lilrb4a", "Cytip", "Dusp1", "Klf2", "Vim", "Capg", "Lamp1", "Anxa2", "Npc2", "Rgs2", "Selplg", "Cst3", "Ctsa", "H2-DMa", "Prkcd", "Sh3bgrl3", "Ypel3"], "Myocyte": ["Cdh11", "Pja1", "Serpine2", "Ecm1", "Tmem9", "Alpl", "Gfi1b", "Ccdc167", "Gar1", "Prdx3", "Chtop", "Tuba1a", "Tango2", "Smim1", "Hypk", "Llph", "Tspo2", "Paip2", "Gm10039", "Mcrs1", "Cetn3", "Gadd45g", "Gm1821", "Yipf4", "Rnf4", "Id3", "Snhg6", "Bmp1", "Ssb", "Farsb", "Slc29a1", "Gja1", "Etfa", "Adk", "Bet1l", "Sh3glb1", "Ost4", "Gm10269", "Snhg5", "Sap18", "Mrpl35", "Rexo2", "Mettl23", "Anxa5", "Gm8797", "Rpl28-ps1", "Mtx2", "Rps15a-ps6", "Atp5l", "Cycs"], "Neural progenitor cell": ["Pfas", "Gm17494", "Gm6563", "Adipoq", "Mylpf", "Capn15", "Tatdn1", "Ect2", "R3hcc1", "Fbxo36", "Exosc1", "Kif20a", "Ppat", "Bex4", "Gm10146", "Klhl5", "Wdr46", "Smco4", "Plscr1", "Rps11-ps1", "Orc6", "Chchd5", "Arrb1", "Retsat", "Stx4a", "Gm8451", "Mpg", "Hscb", "Apopt1", "Dhrs4", "Pbx4", "Cstf3", "Smim10l1", "Tm2d2", "Ptpn2", "Epas1", "Sphk1", "Pop5", "Tmem11", "Wdr43", "Brd8", "Spata24", "Mettl26", "Bloc1s2", "Gm15536", "Tomm20", "Rhoc", "Acads", "Pigp", "Nol6"], "Neutrophil": ["Rac2", "Hp", "Serpinb1a", "S100a9", "S100a11", "Prdx5", "Pkm", "Coro1a", "Camp", "Hmgn2", "Ngp", "Pglyrp1", "Tuba4a", "Anxa1", "Arpc1b", "Cyba", "Lta4h", "Gpi1", "Arpc2", "Arhgdib", "S100a8", "Fcnb", "Tmsb4x", "I830127L07Rik", "Prtn3", "Pfn1", "Tkt", "Wfdc21", "Aldh2", "Chil3", "Msrb1", "Lcn2", "Ltf", "Ms4a3", "Tspo", "Txn1", "Gstm1", "Cybb", "Tagln2", "Taldo1", "Cd177", "Nkg7", "Alox5ap", "Ifitm6", "Cotl1", "Mpo", "Cebpe", "Elane", "Gapdh", "Gmfg"], "Plasma cell": ["Igkc", "Jchain", "Ighm", "Igha", "Iglc2", "Iglv1", "Iglc1", "Ms4a1", "Ly6d", "Mzb1", "Iglc3", "Txndc5", "Ly6a", "Cd79a", "Cd79b", "Cd19", "Fcrla", "Cnp", "Siglecg", "Cd74", "Pafah1b3", "Pou2af1", "Dnajc7", "Xbp1", "Edem1", "Herpud1", "Shisa5", "Creld2", "Rps27rt", "Ifi27l2a", "Chchd10", "Ly6e", "Hsp90b1", "Tmem123", "Ctss", "Arpc5l", "Ptprcap", "B2m", "Sec11c", "Vpreb3", "Btg2", "Serp1", "Selenow", "Ypel3", "Slc3a2", "Rexo2", "H2-D1", "H2-K1", "Klf2", "Serinc3"], "Proliferating cell": ["Olfr74", "Gm44745", "Pcdhb4", "Mybphl", "Dnah12", "Gm15627", "Gm42798", "Gm23444", "Gm23143", "Syne3", "Dph7", "Enkur", "Gm6142", "5830454E08Rik", "Sesn3", "1700029I15Rik", "Atpaf1", "Zfp935", "Slc25a33", "Slc41a3", "Gm19412", "Fbxo44", "Zfp951", "Mpl", "Kif3b", "Iqcd", "Nars2", "C130036L24Rik", "Bmf", "Pfn2", "Cyp51", "Slc22a17", "Hsd17b7", "Rsad1", "Slc25a13", "Senp3", "Kbtbd6", "Alg10b", "Efnb2", "Neil1", "Lrrc56", "C330006A16Rik", "Pced1b", "Amotl1", "Zfp52", "Chn2", "Gm29257", "Pcnx3", "Dag1", "Ryk"], "Secretory alveoli cell": ["Gm20517", "9330179D12Rik", "Gm10244", "Chrnb1", "Zfp239", "Camk2n1", "Kifc3", "Zfp317", "Cd276", "Ercc6", "Aldh1l2", "Gm11714", "4632415L05Rik", "Rab12", "Stap2", "Socs1", "Phldb1", "Gpr153", "Rasip1", "Mir142", "C2cd3", "Mex3c", "Samd1", "Mtfmt", "Foxp4", "Mgat4b", "Pcsk5", "St6galnac6", "Gnb4", "Tcf12", "G430095P16Rik", "Kat6a", "Stx17", "Pax5", "Slc35a1", "Satb2", "Zfp87", "Senp6", "Txnrd1", "Tmem167b", "Zfp655", "Gm17066", "Mefv", "Saysd1", "Nploc4", "Ndrg3", "Anks3", "Ilf3", "Fam160b1", "Ncoa4"], "Smooth muscle cell": ["Acta2", "Myl9", "Tpm2", "Tagln", "Myh11", "Sparcl1", "Mustn1", "Mylk", "Gm13861", "Sncg", "Aoc3", "Olfr558", "Ppp1r14a", "Pln", "Nrip2", "Bcam", "Des", "Rasl11a", "Rrad", "Notch3", "Pcp4l1", "Prss23", "Tinagl1", "Igfbp5", "Rarres2", "Ndufa4l2", "Errfi1", "Aspn", "Cald1", "Hspb1", "Cav1", "Igfbp7", "Tpm1", "Prkcdbp", "Tns1", "Hspb2", "Atf3", "Pdgfa", "Crip1", "Hes1", "Ppp1r15a", "Nr4a1", "Timp3", "Cd151", "Map1lc3a", "Mfge8", "Fxyd1", "Egr1", "Fos", "Atp2a2"], "Spermatogonia": ["Gm7628", "Gm37621", "Jsrp1", "Lhcgr", "Gm14807", "Rprm", "Gm16585", "Fam184a", "Nap1l3", "Gm20467", "Hoxb5", "Cyp7b1", "Gm13181", "Camsap1", "Tssk4", "B230303O12Rik", "Hnf4a", "Ninl", "Gm16575", "Grtp1", "4930513N10Rik", "Podnl1", "Amigo1", "Taf4b", "Arhgap32", "Amigo2", "1700084E18Rik", "Triqk", "Adora2a", "Stxbp4", "4732416N19Rik", "Stau2", "Afp", "Gm8213", "Myo6", "Zfp979", "Cdk20", "Gm11518", "Galnt12", "Esr1", "Gm17786", "A930041C12Rik", "Myl10", "1700028N14Rik", "Zfp12", "Ripk2", "B230307C23Rik", "Dkkl1", "Slc39a4", "Gm27029"], "T cell": ["Ccl5", "Ms4a4b", "Trbc1", "Klrd1", "Trbc2", "Ctsw", "Lck", "Thy1", "AW112010", "Gimap4", "H2-Q7", "Gimap6", "Ltb", "Shisa5", "Il2rg", "Ptprcap", "Tmsb10", "S100a10", "Ptprc", "Id2", "H2-K1", "Rps27", "H2-D1", "Selplg", "Rps23-ps1", "B2m", "Apobec3", "Gm8797", "Eef1a1", "Rps15a", "Rpl4", "Rpl18a", "Hcst", "Crip1", "Ly6e", "Mbnl1", "Rpl3", "Rps14", "Gm14303", "Malat1", "Rps11", "Rps24", "Ypel3", "Rps3", "Gm15427", "Rps6", "Rps23", "Rpl8", "Rpl37a", "Rps3a1"], "Unknown": ["Clps", "Gm23127", "Ddah1", "Ism1", "6330549D23Rik", "Rsl1", "Asb16", "Kcnb1", "Lrp3", "Angpt4", "Ercc5", "Fmo1", "Gm29521", "P4htm", "Gdpgp1", "Tbx15", "Fzd7", "P3h3", "Gm44067", "Hspa1b", "Slfn10-ps", "Zfp629", "Brat1", "Aven", "Irak2", "Cdr2", "A130010J15Rik", "Gdpd2", "Gm9803", "Mettl17", "2810002D19Rik", "Gm9320", "4933404O12Rik", "Wdr60", "Zfp961", "Gm10020", "Limch1", "Glmn", "Pank1", "Coil", "Taf8", "Gm17786", "Xylt2", "Aff3", "Rab38", "Lipo3", "Tut1", "Kdm3a", "Rap2b", "Cfap126"]}