{"B cell": ["Ptprc", "Ptprc", "Cr2", "Fcer1g", "Cd3e"], "T cell": ["Cd3e", "Cd3e", "Tcf7", "Thy1", "Trbc2"], "T follicular helper cell": ["Bcl6", "Pdcd1", "Pdcd1"], "endothelial cell": ["Csf1r", "Lyve1", "Lyve1", "Lyve1", "Pdpn", "Pecam1", "Prox1", "Prox1", "Vegfc", "Vegfc", "Vegfd"], "endothelial cell of lymphatic vessel": ["Cp", "Lyve1", "Lyve1", "Lyve1", "Lyve1", "Prox1", "Prox1", "Vegfc", "Vegfc", "Vegfd"], "fibroblast": ["Ccl19"], "group 2 innate lymphoid cell": ["Klrg1", "Ly6a"], "immature B cell": ["Ptprc", "Igkv14-126"], "lymphocyte": ["Ptprc", "Il7r", "Pdcd1"], "macrophage": ["Cd68"], "monocyte": ["Ccr2", "Fcgr2b"], "plasmacytoid dendritic cell": ["Ccr9", "Ly6d", "Siglech"], "precursor B cell": ["Il2ra"], "pro-B cell": ["Ptprc"]}